restore.py
restore_tool-1.0.3.data/scripts/restore.py
restore_tool-1.0.3.dist-info/DESCRIPTION.rst
restore_tool-1.0.3.dist-info/METADATA
restore_tool-1.0.3.dist-info/RECORD
restore_tool-1.0.3.dist-info/WHEEL
restore_tool-1.0.3.dist-info/entry_points.txt
restore_tool-1.0.3.dist-info/metadata.json
restore_tool-1.0.3.dist-info/top_level.txt
