Metadata-Version: 2.0
Name: restore-tool
Version: 1.0.3
Summary: A simple tool to reconcile difference between backup and restore
Home-page: UNKNOWN
Author: David Yu
Author-email: david.yu@blockchaintech.net.au
License: UNKNOWN
Keywords: wallet restore reconcile
Platform: UNKNOWN
Classifier: Development Status :: 3 - Alpha
Classifier: Intended Audience :: Developers
Classifier: License :: OSI Approved :: MIT License
Classifier: Environment :: Console
Classifier: Programming Language :: Python :: 2
Classifier: Programming Language :: Python :: 2.7
Classifier: Programming Language :: Python :: 3
Classifier: Programming Language :: Python :: 3.4
Classifier: Programming Language :: Python :: 3.5
Classifier: Programming Language :: Python :: 3.6
Requires-Dist: Click
Requires-Dist: python-bitcoinrpc
